zdpytools/__init__.py
zdpytools/aihubmax/__init__.py
zdpytools/aihubmax/client.py
zdpytools/aihubmax/const.py
zdpytools/aihubmax/exception.py
zdpytools/autodl/__init__.py
zdpytools/autodl/client.py
zdpytools/autodl/const.py
zdpytools/autodl/exception.py
zdpytools/feishu/BaseModel.py
zdpytools/feishu/Feishu.py
zdpytools/feishu/FeishuBase.py
zdpytools/feishu/__init__.py
zdpytools/feishu/const.py
zdpytools/feishu/exception.py
zdpytools/feishu/webhook.py
zdpytools/utils/Oss.py
zdpytools/utils/__init__.py
zdpytools/utils/download.py
zdpytools/utils/log.py
zdpytools-0.1.45.dist-info/LICENSE
zdpytools-0.1.45.dist-info/METADATA
zdpytools-0.1.45.dist-info/WHEEL
zdpytools-0.1.45.dist-info/top_level.txt
zdpytools-0.1.45.dist-info/RECORD
