Metadata-Version: 2.1
Name: zdpytools
Version: 0.1.45
Summary: Python工具集，包含飞书API、AutoDL API和日志工具
Home-page: https://github.com/zhidateam/zdpytools
Author: zhidateam
Author-email: zhidateam@163.com
License: UNKNOWN
Platform: UNKNOWN
Classifier: Programming Language :: Python :: 3
Classifier: License :: OSI Approved :: MIT License
Classifier: Operating System :: OS Independent
Requires-Python: >=3.8
License-File: LICENSE
Requires-Dist: loguru (>=0.7.3)
Requires-Dist: httpx (>=0.27.2)
Requires-Dist: pyyaml (>=6.0.2)
Requires-Dist: oss2 (>=2.19.1)
